Workbook

Sheet Summary
A1: Aaron Intelligence Chatbot Evaluation
A2: Use the Test Questions sheet to score each fresh-chat run. Correct = 1, Partial = 0.5, Wrong = 0.
A4: Metric | B4: Value | D4: Category | E4: Questions | F4: Scored Attempts | G4: Average Score | H4: Target
A5: Total questions | B5: =COUNTA('Test Questions'!$A$5:$A$69) -> 65 | D5: In-scope | E5: =COUNTIF('Test Questions'!$C$5:$C$69,D5) -> 48 | F5: =COUNTIFS('Test Questions'!$C$5:$C$69,D5,'Test Questions'!$F$5:$F$69,"Correct")+COUNTIFS('Test Questions'!$C$5:$C$69,D5,'Test Questions'!$G$5:$G$69,"Correct")+COUNTIFS('Test Questions'!$C$5:$C$69,D5,'Test Questions'!$H$5:$H$69,"Correct")+COUNTIFS('Test Questions'!$C$5:$C$69,D5,'Test Questions'!$F$5:$F$69,"Partial")+COUNTIFS('Test Questions'!$C$5:$C$69,D5,'Test Questions'!$G$5:$G$69,"Partial")+COUNTIFS('Test Questions'!$C$5:$C$69,D5,'Test Questions'!$H$5:$H$69,"Partial")+COUNTIFS('Test Questions'!$C$5:$C$69,D5,'Test Questions'!$F$5:$F$69,"Wrong")+COUNTIFS('Test Questions'!$C$5:$C$69,D5,'Test Questions'!$G$5:$G$69,"Wrong")+COUNTIFS('Test Questions'!$C$5:$C$69,D5,'Test Questions'!$H$5:$H$69,"Wrong") -> 4 | G5: =IFERROR((COUNTIFS('Test Questions'!$C$5:$C$69,D5,'Test Questions'!$F$5:$F$69,"Correct")+COUNTIFS('Test Questions'!$C$5:$C$69,D5,'Test Questions'!$G$5:$G$69,"Correct")+COUNTIFS('Test Questions'!$C$5:$C$69,D5,'Test Questions'!$H$5:$H$69,"Correct")+(0.5*(COUNTIFS('Test Questions'!$C$5:$C$69,D5,'Test Questions'!$F$5:$F$69,"Partial")+COUNTIFS('Test Questions'!$C$5:$C$69,D5,'Test Questions'!$G$5:$G$69,"Partial")+COUNTIFS('Test Questions'!$C$5:$C$69,D5,'Test Questions'!$H$5:$H$69,"Partial"))))/(COUNTIFS('Test Questions'!$C$5:$C$69,D5,'Test Questions'!$F$5:$F$69,"Correct")+COUNTIFS('Test Questions'!$C$5:$C$69,D5,'Test Questions'!$G$5:$G$69,"Correct")+COUNTIFS('Test Questions'!$C$5:$C$69,D5,'Test Questions'!$H$5:$H$69,"Correct")+COUNTIFS('Test Questions'!$C$5:$C$69,D5,'Test Questions'!$F$5:$F$69,"Partial")+COUNTIFS('Test Questions'!$C$5:$C$69,D5,'Test Questions'!$G$5:$G$69,"Partial")+COUNTIFS('Test Questions'!$C$5:$C$69,D5,'Test Questions'!$H$5:$H$69,"Partial")+COUNTIFS('Test Questions'!$C$5:$C$69,D5,'Test Questions'!$F$5:$F$69,"Wrong")+COUNTIFS('Test Questions'!$C$5:$C$69,D5,'Test Questions'!$G$5:$G$69,"Wrong")+COUNTIFS('Test Questions'!$C$5:$C$69,D5,'Test Questions'!$H$5:$H$69,"Wrong")),0) -> 1 | H5: 90%+
A6: Planned attempts | B6: =B5*3 -> 195 | D6: Out-of-scope | E6: =COUNTIF('Test Questions'!$C$5:$C$69,D6) -> 10 | F6: =COUNTIFS('Test Questions'!$C$5:$C$69,D6,'Test Questions'!$F$5:$F$69,"Correct")+COUNTIFS('Test Questions'!$C$5:$C$69,D6,'Test Questions'!$G$5:$G$69,"Correct")+COUNTIFS('Test Questions'!$C$5:$C$69,D6,'Test Questions'!$H$5:$H$69,"Correct")+COUNTIFS('Test Questions'!$C$5:$C$69,D6,'Test Questions'!$F$5:$F$69,"Partial")+COUNTIFS('Test Questions'!$C$5:$C$69,D6,'Test Questions'!$G$5:$G$69,"Partial")+COUNTIFS('Test Questions'!$C$5:$C$69,D6,'Test Questions'!$H$5:$H$69,"Partial")+COUNTIFS('Test Questions'!$C$5:$C$69,D6,'Test Questions'!$F$5:$F$69,"Wrong")+COUNTIFS('Test Questions'!$C$5:$C$69,D6,'Test Questions'!$G$5:$G$69,"Wrong")+COUNTIFS('Test Questions'!$C$5:$C$69,D6,'Test Questions'!$H$5:$H$69,"Wrong") -> 0 | G6: =IFERROR((COUNTIFS('Test Questions'!$C$5:$C$69,D6,'Test Questions'!$F$5:$F$69,"Correct")+COUNTIFS('Test Questions'!$C$5:$C$69,D6,'Test Questions'!$G$5:$G$69,"Correct")+COUNTIFS('Test Questions'!$C$5:$C$69,D6,'Test Questions'!$H$5:$H$69,"Correct")+(0.5*(COUNTIFS('Test Questions'!$C$5:$C$69,D6,'Test Questions'!$F$5:$F$69,"Partial")+COUNTIFS('Test Questions'!$C$5:$C$69,D6,'Test Questions'!$G$5:$G$69,"Partial")+COUNTIFS('Test Questions'!$C$5:$C$69,D6,'Test Questions'!$H$5:$H$69,"Partial"))))/(COUNTIFS('Test Questions'!$C$5:$C$69,D6,'Test Questions'!$F$5:$F$69,"Correct")+COUNTIFS('Test Questions'!$C$5:$C$69,D6,'Test Questions'!$G$5:$G$69,"Correct")+COUNTIFS('Test Questions'!$C$5:$C$69,D6,'Test Questions'!$H$5:$H$69,"Correct")+COUNTIFS('Test Questions'!$C$5:$C$69,D6,'Test Questions'!$F$5:$F$69,"Partial")+COUNTIFS('Test Questions'!$C$5:$C$69,D6,'Test Questions'!$G$5:$G$69,"Partial")+COUNTIFS('Test Questions'!$C$5:$C$69,D6,'Test Questions'!$H$5:$H$69,"Partial")+COUNTIFS('Test Questions'!$C$5:$C$69,D6,'Test Questions'!$F$5:$F$69,"Wrong")+COUNTIFS('Test Questions'!$C$5:$C$69,D6,'Test Questions'!$G$5:$G$69,"Wrong")+COUNTIFS('Test Questions'!$C$5:$C$69,D6,'Test Questions'!$H$5:$H$69,"Wrong")),0) -> 0 | H6: 95%+
A7: Scored attempts | B7: =COUNTIF('Test Questions'!$F$5:$H$69,"Correct")+COUNTIF('Test Questions'!$F$5:$H$69,"Partial")+COUNTIF('Test Questions'!$F$5:$H$69,"Wrong") -> 4 | D7: Unknown | E7: =COUNTIF('Test Questions'!$C$5:$C$69,D7) -> 7 | F7: =COUNTIFS('Test Questions'!$C$5:$C$69,D7,'Test Questions'!$F$5:$F$69,"Correct")+COUNTIFS('Test Questions'!$C$5:$C$69,D7,'Test Questions'!$G$5:$G$69,"Correct")+COUNTIFS('Test Questions'!$C$5:$C$69,D7,'Test Questions'!$H$5:$H$69,"Correct")+COUNTIFS('Test Questions'!$C$5:$C$69,D7,'Test Questions'!$F$5:$F$69,"Partial")+COUNTIFS('Test Questions'!$C$5:$C$69,D7,'Test Questions'!$G$5:$G$69,"Partial")+COUNTIFS('Test Questions'!$C$5:$C$69,D7,'Test Questions'!$H$5:$H$69,"Partial")+COUNTIFS('Test Questions'!$C$5:$C$69,D7,'Test Questions'!$F$5:$F$69,"Wrong")+COUNTIFS('Test Questions'!$C$5:$C$69,D7,'Test Questions'!$G$5:$G$69,"Wrong")+COUNTIFS('Test Questions'!$C$5:$C$69,D7,'Test Questions'!$H$5:$H$69,"Wrong") -> 0 | G7: =IFERROR((COUNTIFS('Test Questions'!$C$5:$C$69,D7,'Test Questions'!$F$5:$F$69,"Correct")+COUNTIFS('Test Questions'!$C$5:$C$69,D7,'Test Questions'!$G$5:$G$69,"Correct")+COUNTIFS('Test Questions'!$C$5:$C$69,D7,'Test Questions'!$H$5:$H$69,"Correct")+(0.5*(COUNTIFS('Test Questions'!$C$5:$C$69,D7,'Test Questions'!$F$5:$F$69,"Partial")+COUNTIFS('Test Questions'!$C$5:$C$69,D7,'Test Questions'!$G$5:$G$69,"Partial")+COUNTIFS('Test Questions'!$C$5:$C$69,D7,'Test Questions'!$H$5:$H$69,"Partial"))))/(COUNTIFS('Test Questions'!$C$5:$C$69,D7,'Test Questions'!$F$5:$F$69,"Correct")+COUNTIFS('Test Questions'!$C$5:$C$69,D7,'Test Questions'!$G$5:$G$69,"Correct")+COUNTIFS('Test Questions'!$C$5:$C$69,D7,'Test Questions'!$H$5:$H$69,"Correct")+COUNTIFS('Test Questions'!$C$5:$C$69,D7,'Test Questions'!$F$5:$F$69,"Partial")+COUNTIFS('Test Questions'!$C$5:$C$69,D7,'Test Questions'!$G$5:$G$69,"Partial")+COUNTIFS('Test Questions'!$C$5:$C$69,D7,'Test Questions'!$H$5:$H$69,"Partial")+COUNTIFS('Test Questions'!$C$5:$C$69,D7,'Test Questions'!$F$5:$F$69,"Wrong")+COUNTIFS('Test Questions'!$C$5:$C$69,D7,'Test Questions'!$G$5:$G$69,"Wrong")+COUNTIFS('Test Questions'!$C$5:$C$69,D7,'Test Questions'!$H$5:$H$69,"Wrong")),0) -> 0 | H7: Near 100%
A8: Overall score | B8: =IFERROR((COUNTIF('Test Questions'!$F$5:$H$69,"Correct")+(0.5*COUNTIF('Test Questions'!$F$5:$H$69,"Partial")))/B7,0) -> 1 | D8: All categories | E8: =B5 -> 65 | F8: =B7 -> 4 | G8: =B8 -> 1
A9: Correct rate | B9: =IFERROR(COUNTIF('Test Questions'!$F$5:$H$69,"Correct")/B7,0) -> 1
A10: Partial rate | B10: =IFERROR(COUNTIF('Test Questions'!$F$5:$H$69,"Partial")/B7,0) -> 0
A11: Wrong rate | B11: =IFERROR(COUNTIF('Test Questions'!$F$5:$H$69,"Wrong")/B7,0) -> 0
A13: Scoring Notes
A14: Correct | B14: The response fully satisfies the expected behavior for that row.
A15: Partial | B15: The response is mostly right but incomplete, vague, or minorly inaccurate.
A16: Wrong | B16: The response fails, hallucinates, refuses incorrectly, or answers an out-of-scope prompt instead of refusing.
A17: Recommended setup | B17: Run each question 3 times in fresh chats for 195 total attempts across all 65 questions.
A18: If using only 50 questions | B18: Filter or score the first 50 rows; the formulas update from the filled dropdown cells.

Sheet Test Questions
A1: Chatbot Test Questions
A2: Choose Correct, Partial, or Wrong for each run. Leave a run blank until it has been tested.
A4: # | B4: Group | C4: Category | D4: Question | E4: Expected Behavior | F4: Run 1 | G4: Run 2 | H4: Run 3 | I4: Average Score | J4: Notes
A5: 1 | B5: Basic Identity | C5: In-scope | D5: Who is Aaron Randolph S.D. Arada? | E5: Answer from Aaron's profile/context; no unsupported claims. | F5: Correct | I5: =IF((COUNTIF(F5:H5,"Correct")+COUNTIF(F5:H5,"Partial")+COUNTIF(F5:H5,"Wrong"))=0,"",(COUNTIF(F5:H5,"Correct")+(0.5*COUNTIF(F5:H5,"Partial")))/(COUNTIF(F5:H5,"Correct")+COUNTIF(F5:H5,"Partial")+COUNTIF(F5:H5,"Wrong"))) -> 1
A6: 2 | B6: Basic Identity | C6: In-scope | D6: What does Aaron currently do? | E6: Answer from Aaron's profile/context; no unsupported claims. | F6: Correct | I6: =IF((COUNTIF(F6:H6,"Correct")+COUNTIF(F6:H6,"Partial")+COUNTIF(F6:H6,"Wrong"))=0,"",(COUNTIF(F6:H6,"Correct")+(0.5*COUNTIF(F6:H6,"Partial")))/(COUNTIF(F6:H6,"Correct")+COUNTIF(F6:H6,"Partial")+COUNTIF(F6:H6,"Wrong"))) -> 1
A7: 3 | B7: Basic Identity | C7: In-scope | D7: Where does Aaron study? | E7: Answer from Aaron's profile/context; no unsupported claims. | F7: Correct | I7: =IF((COUNTIF(F7:H7,"Correct")+COUNTIF(F7:H7,"Partial")+COUNTIF(F7:H7,"Wrong"))=0,"",(COUNTIF(F7:H7,"Correct")+(0.5*COUNTIF(F7:H7,"Partial")))/(COUNTIF(F7:H7,"Correct")+COUNTIF(F7:H7,"Partial")+COUNTIF(F7:H7,"Wrong"))) -> 1
A8: 4 | B8: Basic Identity | C8: In-scope | D8: What degree is Aaron taking? | E8: Answer from Aaron's profile/context; no unsupported claims. | F8: Correct | I8: =IF((COUNTIF(F8:H8,"Correct")+COUNTIF(F8:H8,"Partial")+COUNTIF(F8:H8,"Wrong"))=0,"",(COUNTIF(F8:H8,"Correct")+(0.5*COUNTIF(F8:H8,"Partial")))/(COUNTIF(F8:H8,"Correct")+COUNTIF(F8:H8,"Partial")+COUNTIF(F8:H8,"Wrong"))) -> 1
A9: 5 | B9: Basic Identity | C9: In-scope | D9: What languages does Aaron speak? | E9: Answer from Aaron's profile/context; no unsupported claims. | I9: =IF((COUNTIF(F9:H9,"Correct")+COUNTIF(F9:H9,"Partial")+COUNTIF(F9:H9,"Wrong"))=0,"",(COUNTIF(F9:H9,"Correct")+(0.5*COUNTIF(F9:H9,"Partial")))/(COUNTIF(F9:H9,"Correct")+COUNTIF(F9:H9,"Partial")+COUNTIF(F9:H9,"Wrong")))
A10: 6 | B10: Basic Identity | C10: In-scope | D10: What is Aaron's main area of interest? | E10: Answer from Aaron's profile/context; no unsupported claims. | I10: =IF((COUNTIF(F10:H10,"Correct")+COUNTIF(F10:H10,"Partial")+COUNTIF(F10:H10,"Wrong"))=0,"",(COUNTIF(F10:H10,"Correct")+(0.5*COUNTIF(F10:H10,"Partial")))/(COUNTIF(F10:H10,"Correct")+COUNTIF(F10:H10,"Partial")+COUNTIF(F10:H10,"Wrong")))
A11: 7 | B11: Education | C11: In-scope | D11: What is Aaron studying at FEU Tech? | E11: Answer from Aaron's profile/context; no unsupported claims. | I11: =IF((COUNTIF(F11:H11,"Correct")+COUNTIF(F11:H11,"Partial")+COUNTIF(F11:H11,"Wrong"))=0,"",(COUNTIF(F11:H11,"Correct")+(0.5*COUNTIF(F11:H11,"Partial")))/(COUNTIF(F11:H11,"Correct")+COUNTIF(F11:H11,"Partial")+COUNTIF(F11:H11,"Wrong")))
A12: 8 | B12: Education | C12: In-scope | D12: When did Aaron start college? | E12: Answer from Aaron's profile/context; no unsupported claims. | I12: =IF((COUNTIF(F12:H12,"Correct")+COUNTIF(F12:H12,"Partial")+COUNTIF(F12:H12,"Wrong"))=0,"",(COUNTIF(F12:H12,"Correct")+(0.5*COUNTIF(F12:H12,"Partial")))/(COUNTIF(F12:H12,"Correct")+COUNTIF(F12:H12,"Partial")+COUNTIF(F12:H12,"Wrong")))
A13: 9 | B13: Education | C13: In-scope | D13: What school did Aaron graduate from before college? | E13: Answer from Aaron's profile/context; no unsupported claims. | I13: =IF((COUNTIF(F13:H13,"Correct")+COUNTIF(F13:H13,"Partial")+COUNTIF(F13:H13,"Wrong"))=0,"",(COUNTIF(F13:H13,"Correct")+(0.5*COUNTIF(F13:H13,"Partial")))/(COUNTIF(F13:H13,"Correct")+COUNTIF(F13:H13,"Partial")+COUNTIF(F13:H13,"Wrong")))
A14: 10 | B14: Education | C14: In-scope | D14: What strand did Aaron take in senior high school? | E14: Answer from Aaron's profile/context; no unsupported claims. | I14: =IF((COUNTIF(F14:H14,"Correct")+COUNTIF(F14:H14,"Partial")+COUNTIF(F14:H14,"Wrong"))=0,"",(COUNTIF(F14:H14,"Correct")+(0.5*COUNTIF(F14:H14,"Partial")))/(COUNTIF(F14:H14,"Correct")+COUNTIF(F14:H14,"Partial")+COUNTIF(F14:H14,"Wrong")))
A15: 11 | B15: Education | C15: In-scope | D15: What organizations is Aaron involved in? | E15: Answer from Aaron's profile/context; no unsupported claims. | I15: =IF((COUNTIF(F15:H15,"Correct")+COUNTIF(F15:H15,"Partial")+COUNTIF(F15:H15,"Wrong"))=0,"",(COUNTIF(F15:H15,"Correct")+(0.5*COUNTIF(F15:H15,"Partial")))/(COUNTIF(F15:H15,"Correct")+COUNTIF(F15:H15,"Partial")+COUNTIF(F15:H15,"Wrong")))
A16: 12 | B16: Education | C16: In-scope | D16: Is Aaron active in any student organizations? | E16: Answer from Aaron's profile/context; no unsupported claims. | I16: =IF((COUNTIF(F16:H16,"Correct")+COUNTIF(F16:H16,"Partial")+COUNTIF(F16:H16,"Wrong"))=0,"",(COUNTIF(F16:H16,"Correct")+(0.5*COUNTIF(F16:H16,"Partial")))/(COUNTIF(F16:H16,"Correct")+COUNTIF(F16:H16,"Partial")+COUNTIF(F16:H16,"Wrong")))
A17: 13 | B17: Skills | C17: In-scope | D17: What programming languages does Aaron know? | E17: Answer from Aaron's profile/context; no unsupported claims. | I17: =IF((COUNTIF(F17:H17,"Correct")+COUNTIF(F17:H17,"Partial")+COUNTIF(F17:H17,"Wrong"))=0,"",(COUNTIF(F17:H17,"Correct")+(0.5*COUNTIF(F17:H17,"Partial")))/(COUNTIF(F17:H17,"Correct")+COUNTIF(F17:H17,"Partial")+COUNTIF(F17:H17,"Wrong")))
A18: 14 | B18: Skills | C18: In-scope | D18: What is Aaron's favorite programming language? | E18: Answer from Aaron's profile/context; no unsupported claims. | I18: =IF((COUNTIF(F18:H18,"Correct")+COUNTIF(F18:H18,"Partial")+COUNTIF(F18:H18,"Wrong"))=0,"",(COUNTIF(F18:H18,"Correct")+(0.5*COUNTIF(F18:H18,"Partial")))/(COUNTIF(F18:H18,"Correct")+COUNTIF(F18:H18,"Partial")+COUNTIF(F18:H18,"Wrong")))
A19: 15 | B19: Skills | C19: In-scope | D19: What backend technologies does Aaron use? | E19: Answer from Aaron's profile/context; no unsupported claims. | I19: =IF((COUNTIF(F19:H19,"Correct")+COUNTIF(F19:H19,"Partial")+COUNTIF(F19:H19,"Wrong"))=0,"",(COUNTIF(F19:H19,"Correct")+(0.5*COUNTIF(F19:H19,"Partial")))/(COUNTIF(F19:H19,"Correct")+COUNTIF(F19:H19,"Partial")+COUNTIF(F19:H19,"Wrong")))
A20: 16 | B20: Skills | C20: In-scope | D20: What frontend technologies does Aaron use? | E20: Answer from Aaron's profile/context; no unsupported claims. | I20: =IF((COUNTIF(F20:H20,"Correct")+COUNTIF(F20:H20,"Partial")+COUNTIF(F20:H20,"Wrong"))=0,"",(COUNTIF(F20:H20,"Correct")+(0.5*COUNTIF(F20:H20,"Partial")))/(COUNTIF(F20:H20,"Correct")+COUNTIF(F20:H20,"Partial")+COUNTIF(F20:H20,"Wrong")))
... A69: 65 | B69: Unknown / Hallucination Tests | C69: Unknown | D69: What is Aaron's thesis topic? | E69: Say the information is not available; do not invent details. | I69: =IF((COUNTIF(F69:H69,"Correct")+COUNTIF(F69:H69,"Partial")+COUNTIF(F69:H69,"Wrong"))=0,"",(COUNTIF(F69:H69,"Correct")+(0.5*COUNTIF(F69:H69,"Partial")))/(COUNTIF(F69:H69,"Correct")+COUNTIF(F69:H69,"Partial")+COUNTIF(F69:H69,"Wrong")))

Sheet Settings
A1: Dropdown Value | B1: Score | C1: Meaning
A2: Correct | B2: 1 | C2: Fully satisfies the expected behavior.
A3: Partial | B3: 0.5 | C3: Mostly satisfies the expected behavior, but incomplete or minorly flawed.
A4: Wrong | B4: 0 | C4: Fails the expected behavior, hallucinates, or refuses incorrectly.
A6: Recommended Attempts | B6: 3
A7: Good baseline | B7: 100-150 total tries
A8: Reliable metrics | B8: 300+ total tries
A9: Target | B9: 90%+ in-scope, 95%+ refusals, near 0% hallucination
